{
  "slug": "convert-hours-to-seconds",
  "title": "Convert Hours To Seconds",
  "c": "#include <stdio.h>\n\nint main(){\n    \n    int n;\n    scanf(\"%d\",&n);\n    printf(\"%d\",n*3600);\n    return 0;\n}\n\n//Contributed by Raghav Garg",
  "c-plus-plus": "#include<bits/stdc++.h>\nusing namespace std;\n\nint main()\n{\n    long double sec,hours;\n    // take input\n    cin>>hours;  \n    \n    // 1 hour = 60 minutes = 3600 seconds\n    sec = hours*3600;\n    \n    cout<<sec;  \n}",
  "c-sharp": "using System;\n\nclass MainClass {\n    public static void Main (string[] args) {\n    Console.WriteLine (\"Please enter the hours : \");\n    double hours = Convert.ToDouble(Console.ReadLine());\n    double seconds = hours * 3600;\n    Console.WriteLine(hours+\" hours is \"+seconds+\" seconds\");\n  }\n}\n",
  "f-sharp": "let hoursToSeconds hours : int =\n  hours * 3600\n\nlet seconds = hoursToSeconds 5\n\nprintfn \"Equivalent Seconds : %d\" seconds\n",
  "java": "import java.util.*;\n\npublic class ConvertHoursToSeconds {\n    public static void main(String[] args) {\n        Scanner sc = new Scanner(System.in);\n        int hours = sc.nextInt();\n        long seconds = hours * 60 * 60;\n        System.out.println(seconds);\n        sc.close();\n    }\n}",
  "javascript": "function HoursToSeconds(hours) {\n  // 1 hour = 60 minutes;\n  // 1 minute = 60 seconds;\n  // 1 hour = 60 mins * 60sec = 3600 seconds\n\n  let minutes = hours * 60;\n  let seconds = minutes * 60;\n  return seconds;\n}\n\nconsole.log(HoursToSeconds(5) + \" seconds\");\n",
  "kotlin": "fun main() {\n    print(\"Enter weeks : \")\n    println()\n    var input = readLine()\n\n    try {\n        println(\"$input hours = \" + ConvertHoursToSeconds(input!!.toInt()) + \" seconds\")\n    } catch (exception: Exception) {\n        println(\"Input string was not in a correct format\")\n    }\n\n}\n\nprivate fun ConvertHoursToSeconds(hr: Int): Int {\n    val hoursToSeconds = hr * 3600\n\n    return  hoursToSeconds\n}",
  "ruby": "def hoursToSeconds(hours)\n  hours * 3600\nend\n\nif $PROGRAM_NAME == __FILE__\n  print 'Please enter the hours : '\n  hours = gets.chomp.to_i\n\n  puts \"#{hours} hours is #{hoursToSeconds(hours)} seconds\"\nend\n",
  "swift": "import Swift\nimport Foundation\n\nprint(\"Enter hours: \")\nvar hours = Int(readLine()!)!\nprint(\"Seconds: \", hours * 3600)\n",
  "typescript": "function HoursToSeconds(hours: number) {\n  // 1 hour = 60 minutes;\n  // 1 minute = 60 seconds;\n  // 1 hour = 60 mins * 60sec = 3600 seconds\n\n  const minutes = hours * 60;\n  const seconds = minutes * 60;\n  return seconds;\n}\n\nconsole.log(HoursToSeconds(5) + \" seconds\");\n",
  "description": "\n## Write a program to convert hours to seconds\n\n1 hour = 60 minutes = 3600 seconds\n\n```txt\nInput  : 5\nOutput : 18000\n```\n\n---\n",
  "trackId": 1152,
  "lastUpdated": "2023-08-03T20:39:16Z",
  "contributors": [
    "harshraj8843",
    "anandfresh",
    "aayushxrj",
    "esivakumar26",
    "Sairaviteja27",
    "rksp25",
    "joao-vitor-souza",
    "greeshma-d",
    "grraghav120",
    "shivampipalwa",
    "MufaddalHakim",
    "rahmat-dev",
    "rakibul-islam-raju"
  ],
  "julia": "print(\"Enter the hours : \")\nhours = parse(Float64, readline(stdin))\nseconds = hours * 3600\nprintln(\"Equivalent seconds : \", seconds)\n",
  "scala": "object HelloWorld {\n\tdef main(args: Array[String]): Unit = {\n\t  val hours = scala.io.StdIn.readInt();\n\t  println(\"Seconds: \" + hours * 3600);\n\t}\n}\n",
  "dart": "import 'dart:io';\nvoid main(){\n  print(\"Enter the hours :\");\n  var hours = int.parse(stdin.readLineSync()!);\n  var seconds =  hours * 3600;\n  print('Equivalent seconds  : $seconds');\n}\n",
  "go": "// Created by: Ravi Teja\n// Language: GO\n// Github: https://github.com/Sairaviteja27\n\n// Declare Main Package\npackage main\n\n// Import input output package, lets us use things such as Print\nimport \"fmt\"\n\n// Main Function\nfunc main() {\n\tvar hours int\n\tfmt.Println(\"Enter number of hours :\")\n\tfmt.Scan(&hours)\n\tfmt.Println(\"Number of seconds is \", hours*3600)\n}\n",
  "php": "<?php\n$x = readline('Enter hours: ');\n\n$x1 = $x*60*60;\necho \"Seconds :: $x1.\\n\";\n\n ?>\n",
  "perl": "#!/usr/bin/perl\nuse warnings;\nuse strict;\nprint \"Enter the hours : \";\nmy $hours = <STDIN>;\nmy $seconds = $hours * 3600;\nprint $hours.\" hours is \".$seconds.\" seconds\", \"\\n\";\n",
  "python": "hours = int(input())\n\n# convers to seonds\nseconds = hours * 60 * 60\nprint(seconds)\n",
  "r": "hours = readline(\"hours: \"); \nhours = as.integer(hours);\nseconds = hours * 3600\ncat(\"seconds: \", seconds)\n",
  "rust": "fn convert_hours_to_seconds(hours: u64) -> u64 {\n\treturn hours * 60 * 60;\n}\n\nfn main() {\n\tprintln!(\"{}\", convert_hours_to_seconds(5));\n}",
  "languages": [
    "c",
    "c-plus-plus",
    "c-sharp",
    "f-sharp",
    "java",
    "javascript",
    "kotlin",
    "ruby",
    "swift",
    "typescript",
    "julia",
    "scala",
    "dart",
    "go",
    "php",
    "perl",
    "python",
    "r",
    "rust"
  ]
}